{
  "metadata": {
    "source": "tencent_qfq_daily_history",
    "schema_version": "2.0",
    "snapshot_id": "20260526_historical_58457bdd710d2303",
    "dataset_version": "20260526_historical_58457bdd710d2303",
    "mode": "historical",
    "captured_at": "2026-06-21T10:45:03+08:00",
    "source_time": "2026-05-26T15:00:00+08:00",
    "market_date": "20260526",
    "window_valid": true,
    "is_bootstrap_history": true,
    "history_adjustment": "qfq",
    "requested_trading_days": 20,
    "units": {
      "price": "CNY_per_share_qfq",
      "pct": "percent",
      "amount": "CNY",
      "volume": "upstream_native_unit"
    },
    "limitations": [
      "Historical company names use the current stock universe response.",
      "Historical industry/concept boards and fund-flow rankings are not synthesized.",
      "Some fallback history sources do not provide historical amount or turnover fields; missing values remain null."
    ]
  },
  "derived": {
    "summary": {
      "stock_count": 5189,
      "tradeable_stock_count": 3029,
      "up_count": 1312,
      "down_count": 3810,
      "limit_up_count": 0,
      "broken_limit_count": 0,
      "market_breadth": 0.2561,
      "broken_limit_ratio": 0.0
    },
    "rankings": {
      "top_gainers": [
        {
          "code": "603995",
          "name": "甬金股份",
          "price": 19.28,
          "pct": 10.2975,
          "amount": 0.0,
          "turnover": 0.0,
          "volume_ratio": 0.0,
          "amplitude": 0.0,
          "speed": 0.0,
          "change_5m": 0.0,
          "market_cap_float": 0.0,
          "market_cap_total": 0.0,
          "high": 19.28,
          "low": 17.36,
          "open": 17.4,
          "prev_close": 17.48
        },
        {
          "code": "600378",
          "name": "昊华科技",
          "price": 38.858,
          "pct": 10.1168,
          "amount": 0.0,
          "turnover": 0.0,
          "volume_ratio": 0.0,
          "amplitude": 0.0,
          "speed": 0.0,
          "change_5m": 0.0,
          "market_cap_float": 0.0,
          "market_cap_total": 0.0,
          "high": 38.858,
          "low": 34.768,
          "open": 35.018,
          "prev_close": 35.288
        },
        {
          "code": "002388",
          "name": "新亚制程",
          "price": 6.44,
          "pct": 10.0855,
          "amount": 0.0,
          "turnover": 0.0,
          "volume_ratio": 0.0,
          "amplitude": 0.0,
          "speed": 0.0,
          "change_5m": 0.0,
          "market_cap_float": 0.0,
          "market_cap_total": 0.0,
          "high": 6.44,
          "low": 6.44,
          "open": 6.44,
          "prev_close": 5.85
        },
        {
          "code": "002251",
          "name": "步步高",
          "price": 4.15,
          "pct": 10.0796,
          "amount": 0.0,
          "turnover": 0.0,
          "volume_ratio": 0.0,
          "amplitude": 0.0,
          "speed": 0.0,
          "change_5m": 0.0,
          "market_cap_float": 0.0,
          "market_cap_total": 0.0,
          "high": 4.15,
          "low": 3.74,
          "open": 3.75,
          "prev_close": 3.77
        },
        {
          "code": "600301",
          "name": "华锡有色",
          "price": 60.83,
          "pct": 10.0796,
          "amount": 0.0,
          "turnover": 0.0,
          "volume_ratio": 0.0,
          "amplitude": 0.0,
          "speed": 0.0,
          "change_5m": 0.0,
          "market_cap_float": 0.0,
          "market_cap_total": 0.0,
          "high": 60.83,
          "low": 53.27,
          "open": 54.62,
          "prev_close": 55.26
        },
        {
          "code": "600183",
          "name": "生益科技",
          "price": 127.37,
          "pct": 10.0674,
          "amount": 0.0,
          "turnover": 0.0,
          "volume_ratio": 0.0,
          "amplitude": 0.0,
          "speed": 0.0,
          "change_5m": 0.0,
          "market_cap_float": 0.0,
          "market_cap_total": 0.0,
          "high": 127.37,
          "low": 114.8,
          "open": 114.88,
          "prev_close": 115.72
        },
        {
          "code": "002627",
          "name": "三峡旅游",
          "price": 7.222,
          "pct": 10.0579,
          "amount": 0.0,
          "turnover": 0.0,
          "volume_ratio": 0.0,
          "amplitude": 0.0,
          "speed": 0.0,
          "change_5m": 0.0,
          "market_cap_float": 0.0,
          "market_cap_total": 0.0,
          "high": 7.222,
          "low": 6.492,
          "open": 6.562,
          "prev_close": 6.562
        },
        {
          "code": "002957",
          "name": "科瑞技术",
          "price": 52.57,
          "pct": 10.0481,
          "amount": 0.0,
          "turnover": 0.0,
          "volume_ratio": 0.0,
          "amplitude": 0.0,
          "speed": 0.0,
          "change_5m": 0.0,
          "market_cap_float": 0.0,
          "market_cap_total": 0.0,
          "high": 52.57,
          "low": 44.52,
          "open": 48.3,
          "prev_close": 47.77
        },
        {
          "code": "002585",
          "name": "双星新材",
          "price": 10.85,
          "pct": 10.0406,
          "amount": 0.0,
          "turnover": 0.0,
          "volume_ratio": 0.0,
          "amplitude": 0.0,
          "speed": 0.0,
          "change_5m": 0.0,
          "market_cap_float": 0.0,
          "market_cap_total": 0.0,
          "high": 10.85,
          "low": 9.78,
          "open": 10.05,
          "prev_close": 9.86
        },
        {
          "code": "600635",
          "name": "大众公用",
          "price": 6.03,
          "pct": 10.0365,
          "amount": 0.0,
          "turnover": 0.0,
          "volume_ratio": 0.0,
          "amplitude": 0.0,
          "speed": 0.0,
          "change_5m": 0.0,
          "market_cap_float": 0.0,
          "market_cap_total": 0.0,
          "high": 6.03,
          "low": 5.55,
          "open": 5.57,
          "prev_close": 5.48
        },
        {
          "code": "002185",
          "name": "华天科技",
          "price": 18.648,
          "pct": 10.0307,
          "amount": 0.0,
          "turnover": 0.0,
          "volume_ratio": 0.0,
          "amplitude": 0.0,
          "speed": 0.0,
          "change_5m": 0.0,
          "market_cap_float": 0.0,
          "market_cap_total": 0.0,
          "high": 18.648,
          "low": 18.138,
          "open": 18.648,
          "prev_close": 16.948
        },
        {
          "code": "603353",
          "name": "和顺石油",
          "price": 54.97,
          "pct": 10.028,
          "amount": 0.0,
          "turnover": 0.0,
          "volume_ratio": 0.0,
          "amplitude": 0.0,
          "speed": 0.0,
          "change_5m": 0.0,
          "market_cap_float": 0.0,
          "market_cap_total": 0.0,
          "high": 54.97,
          "low": 50.02,
          "open": 50.02,
          "prev_close": 49.96
        },
        {
          "code": "002733",
          "name": "雄韬股份",
          "price": 32.152,
          "pct": 10.0267,
          "amount": 0.0,
          "turnover": 0.0,
          "volume_ratio": 0.0,
          "amplitude": 0.0,
          "speed": 0.0,
          "change_5m": 0.0,
          "market_cap_float": 0.0,
          "market_cap_total": 0.0,
          "high": 32.152,
          "low": 28.612,
          "open": 29.042,
          "prev_close": 29.222
        },
        {
          "code": "002181",
          "name": "粤 传 媒",
          "price": 14.49,
          "pct": 10.0228,
          "amount": 0.0,
          "turnover": 0.0,
          "volume_ratio": 0.0,
          "amplitude": 0.0,
          "speed": 0.0,
          "change_5m": 0.0,
          "market_cap_float": 0.0,
          "market_cap_total": 0.0,
          "high": 14.49,
          "low": 12.69,
          "open": 12.99,
          "prev_close": 13.17
        },
        {
          "code": "002579",
          "name": "中京电子",
          "price": 15.04,
          "pct": 10.0219,
          "amount": 0.0,
          "turnover": 0.0,
          "volume_ratio": 0.0,
          "amplitude": 0.0,
          "speed": 0.0,
          "change_5m": 0.0,
          "market_cap_float": 0.0,
          "market_cap_total": 0.0,
          "high": 15.04,
          "low": 13.57,
          "open": 13.67,
          "prev_close": 13.67
        },
        {
          "code": "603608",
          "name": "天创时尚",
          "price": 19.11,
          "pct": 10.0173,
          "amount": 0.0,
          "turnover": 0.0,
          "volume_ratio": 0.0,
          "amplitude": 0.0,
          "speed": 0.0,
          "change_5m": 0.0,
          "market_cap_float": 0.0,
          "market_cap_total": 0.0,
          "high": 19.11,
          "low": 17.08,
          "open": 17.08,
          "prev_close": 17.37
        },
        {
          "code": "003036",
          "name": "泰坦股份",
          "price": 61.514,
          "pct": 10.0154,
          "amount": 0.0,
          "turnover": 0.0,
          "volume_ratio": 0.0,
          "amplitude": 0.0,
          "speed": 0.0,
          "change_5m": 0.0,
          "market_cap_float": 0.0,
          "market_cap_total": 0.0,
          "high": 61.514,
          "low": 56.834,
          "open": 57.914,
          "prev_close": 55.914
        },
        {
          "code": "600367",
          "name": "红星发展",
          "price": 29.77,
          "pct": 10.0148,
          "amount": 0.0,
          "turnover": 0.0,
          "volume_ratio": 0.0,
          "amplitude": 0.0,
          "speed": 0.0,
          "change_5m": 0.0,
          "market_cap_float": 0.0,
          "market_cap_total": 0.0,
          "high": 29.77,
          "low": 27.66,
          "open": 27.73,
          "prev_close": 27.06
        },
        {
          "code": "603685",
          "name": "晨丰科技",
          "price": 35.82,
          "pct": 10.0123,
          "amount": 0.0,
          "turnover": 0.0,
          "volume_ratio": 0.0,
          "amplitude": 0.0,
          "speed": 0.0,
          "change_5m": 0.0,
          "market_cap_float": 0.0,
          "market_cap_total": 0.0,
          "high": 35.82,
          "low": 31.95,
          "open": 32.44,
          "prev_close": 32.56
        },
        {
          "code": "601600",
          "name": "中国铝业",
          "price": 12.09,
          "pct": 10.0091,
          "amount": 0.0,
          "turnover": 0.0,
          "volume_ratio": 0.0,
          "amplitude": 0.0,
          "speed": 0.0,
          "change_5m": 0.0,
          "market_cap_float": 0.0,
          "market_cap_total": 0.0,
          "high": 12.09,
          "low": 11.2,
          "open": 11.2,
          "prev_close": 10.99
        },
        {
          "code": "600520",
          "name": "三佳科技",
          "price": 36.82,
          "pct": 10.009,
          "amount": 0.0,
          "turnover": 0.0,
          "volume_ratio": 0.0,
          "amplitude": 0.0,
          "speed": 0.0,
          "change_5m": 0.0,
          "market_cap_float": 0.0,
          "market_cap_total": 0.0,
          "high": 36.82,
          "low": 36.4,
          "open": 36.82,
          "prev_close": 33.47
        },
        {
          "code": "001257",
          "name": "盛龙股份",
          "price": 25.83,
          "pct": 10.0085,
          "amount": 0.0,
          "turnover": 0.0,
          "volume_ratio": 0.0,
          "amplitude": 0.0,
          "speed": 0.0,
          "change_5m": 0.0,
          "market_cap_float": 0.0,
          "market_cap_total": 0.0,
          "high": 25.83,
          "low": 22.64,
          "open": 23.2,
          "prev_close": 23.48
        },
        {
          "code": "600172",
          "name": "黄河旋风",
          "price": 13.3,
          "pct": 10.0083,
          "amount": 0.0,
          "turnover": 0.0,
          "volume_ratio": 0.0,
          "amplitude": 0.0,
          "speed": 0.0,
          "change_5m": 0.0,
          "market_cap_float": 0.0,
          "market_cap_total": 0.0,
          "high": 13.3,
          "low": 12.6,
          "open": 12.74,
          "prev_close": 12.09
        },
        {
          "code": "003004",
          "name": "声迅股份",
          "price": 54.74,
          "pct": 10.008,
          "amount": 0.0,
          "turnover": 0.0,
          "volume_ratio": 0.0,
          "amplitude": 0.0,
          "speed": 0.0,
          "change_5m": 0.0,
          "market_cap_float": 0.0,
          "market_cap_total": 0.0,
          "high": 54.74,
          "low": 47.52,
          "open": 49.3,
          "prev_close": 49.76
        },
        {
          "code": "001376",
          "name": "百通能源",
          "price": 15.28,
          "pct": 10.0072,
          "amount": 0.0,
          "turnover": 0.0,
          "volume_ratio": 0.0,
          "amplitude": 0.0,
          "speed": 0.0,
          "change_5m": 0.0,
          "market_cap_float": 0.0,
          "market_cap_total": 0.0,
          "high": 15.28,
          "low": 13.6,
          "open": 13.78,
          "prev_close": 13.89
        },
        {
          "code": "001331",
          "name": "胜通能源",
          "price": 67.83,
          "pct": 10.0065,
          "amount": 0.0,
          "turnover": 0.0,
          "volume_ratio": 0.0,
          "amplitude": 0.0,
          "speed": 0.0,
          "change_5m": 0.0,
          "market_cap_float": 0.0,
          "market_cap_total": 0.0,
          "high": 67.83,
          "low": 60.8,
          "open": 61.67,
          "prev_close": 61.66
        },
        {
          "code": "605006",
          "name": "山东玻纤",
          "price": 17.92,
          "pct": 10.0061,
          "amount": 0.0,
          "turnover": 0.0,
          "volume_ratio": 0.0,
          "amplitude": 0.0,
          "speed": 0.0,
          "change_5m": 0.0,
          "market_cap_float": 0.0,
          "market_cap_total": 0.0,
          "high": 17.92,
          "low": 15.47,
          "open": 15.88,
          "prev_close": 16.29
        },
        {
          "code": "600584",
          "name": "长电科技",
          "price": 88.19,
          "pct": 10.0037,
          "amount": 0.0,
          "turnover": 0.0,
          "volume_ratio": 0.0,
          "amplitude": 0.0,
          "speed": 0.0,
          "change_5m": 0.0,
          "market_cap_float": 0.0,
          "market_cap_total": 0.0,
          "high": 88.19,
          "low": 81.15,
          "open": 83.0,
          "prev_close": 80.17
        },
        {
          "code": "000506",
          "name": "招金黄金",
          "price": 15.4,
          "pct": 10.0,
          "amount": 0.0,
          "turnover": 0.0,
          "volume_ratio": 0.0,
          "amplitude": 0.0,
          "speed": 0.0,
          "change_5m": 0.0,
          "market_cap_float": 0.0,
          "market_cap_total": 0.0,
          "high": 15.4,
          "low": 13.68,
          "open": 13.96,
          "prev_close": 14.0
        },
        {
          "code": "002552",
          "name": "宝鼎科技",
          "price": 48.18,
          "pct": 10.0,
          "amount": 0.0,
          "turnover": 0.0,
          "volume_ratio": 0.0,
          "amplitude": 0.0,
          "speed": 0.0,
          "change_5m": 0.0,
          "market_cap_float": 0.0,
          "market_cap_total": 0.0,
          "high": 48.18,
          "low": 42.5,
          "open": 44.61,
          "prev_close": 43.8
        },
        {
          "code": "603773",
          "name": "沃格光电",
          "price": 91.54,
          "pct": 9.9976,
          "amount": 0.0,
          "turnover": 0.0,
          "volume_ratio": 0.0,
          "amplitude": 0.0,
          "speed": 0.0,
          "change_5m": 0.0,
          "market_cap_float": 0.0,
          "market_cap_total": 0.0,
          "high": 91.54,
          "low": 83.93,
          "open": 85.79,
          "prev_close": 83.22
        },
        {
          "code": "002896",
          "name": "中大力德",
          "price": 89.68,
          "pct": 9.9963,
          "amount": 0.0,
          "turnover": 0.0,
          "volume_ratio": 0.0,
          "amplitude": 0.0,
          "speed": 0.0,
          "change_5m": 0.0,
          "market_cap_float": 0.0,
          "market_cap_total": 0.0,
          "high": 89.68,
          "low": 86.0,
          "open": 86.0,
          "prev_close": 81.53
        },
        {
          "code": "002886",
          "name": "沃特股份",
          "price": 31.59,
          "pct": 9.993,
          "amount": 0.0,
          "turnover": 0.0,
          "volume_ratio": 0.0,
          "amplitude": 0.0,
          "speed": 0.0,
          "change_5m": 0.0,
          "market_cap_float": 0.0,
          "market_cap_total": 0.0,
          "high": 31.59,
          "low": 28.45,
          "open": 28.6,
          "prev_close": 28.72
        },
        {
          "code": "601958",
          "name": "金钼股份",
          "price": 23.23,
          "pct": 9.9905,
          "amount": 0.0,
          "turnover": 0.0,
          "volume_ratio": 0.0,
          "amplitude": 0.0,
          "speed": 0.0,
          "change_5m": 0.0,
          "market_cap_float": 0.0,
          "market_cap_total": 0.0,
          "high": 23.23,
          "low": 20.58,
          "open": 21.0,
          "prev_close": 21.12
        },
        {
          "code": "002245",
          "name": "蔚蓝锂芯",
          "price": 22.35,
          "pct": 9.9902,
          "amount": 0.0,
          "turnover": 0.0,
          "volume_ratio": 0.0,
          "amplitude": 0.0,
          "speed": 0.0,
          "change_5m": 0.0,
          "market_cap_float": 0.0,
          "market_cap_total": 0.0,
          "high": 22.35,
          "low": 21.0,
          "open": 21.37,
          "prev_close": 20.32
        },
        {
          "code": "605196",
          "name": "华通线缆",
          "price": 44.7,
          "pct": 9.9902,
          "amount": 0.0,
          "turnover": 0.0,
          "volume_ratio": 0.0,
          "amplitude": 0.0,
          "speed": 0.0,
          "change_5m": 0.0,
          "market_cap_float": 0.0,
          "market_cap_total": 0.0,
          "high": 44.7,
          "low": 38.85,
          "open": 40.48,
          "prev_close": 40.64
        },
        {
          "code": "001366",
          "name": "播恩集团",
          "price": 18.61,
          "pct": 9.9882,
          "amount": 0.0,
          "turnover": 0.0,
          "volume_ratio": 0.0,
          "amplitude": 0.0,
          "speed": 0.0,
          "change_5m": 0.0,
          "market_cap_float": 0.0,
          "market_cap_total": 0.0,
          "high": 18.61,
          "low": 16.7,
          "open": 16.92,
          "prev_close": 16.92
        },
        {
          "code": "000510",
          "name": "新金路",
          "price": 18.07,
          "pct": 9.9817,
          "amount": 0.0,
          "turnover": 0.0,
          "volume_ratio": 0.0,
          "amplitude": 0.0,
          "speed": 0.0,
          "change_5m": 0.0,
          "market_cap_float": 0.0,
          "market_cap_total": 0.0,
          "high": 18.07,
          "low": 16.19,
          "open": 16.55,
          "prev_close": 16.43
        },
        {
          "code": "600021",
          "name": "上海电力",
          "price": 20.39,
          "pct": 9.9784,
          "amount": 0.0,
          "turnover": 0.0,
          "volume_ratio": 0.0,
          "amplitude": 0.0,
          "speed": 0.0,
          "change_5m": 0.0,
          "market_cap_float": 0.0,
          "market_cap_total": 0.0,
          "high": 20.39,
          "low": 18.37,
          "open": 18.48,
          "prev_close": 18.54
        },
        {
          "code": "002771",
          "name": "真视通",
          "price": 14.99,
          "pct": 9.978,
          "amount": 0.0,
          "turnover": 0.0,
          "volume_ratio": 0.0,
          "amplitude": 0.0,
          "speed": 0.0,
          "change_5m": 0.0,
          "market_cap_float": 0.0,
          "market_cap_total": 0.0,
          "high": 14.99,
          "low": 13.45,
          "open": 13.55,
          "prev_close": 13.63
        },
        {
          "code": "000509",
          "name": "华塑控股",
          "price": 4.74,
          "pct": 9.9768,
          "amount": 0.0,
          "turnover": 0.0,
          "volume_ratio": 0.0,
          "amplitude": 0.0,
          "speed": 0.0,
          "change_5m": 0.0,
          "market_cap_float": 0.0,
          "market_cap_total": 0.0,
          "high": 4.74,
          "low": 4.34,
          "open": 4.34,
          "prev_close": 4.31
        },
        {
          "code": "600726",
          "name": "华电能源",
          "price": 7.61,
          "pct": 9.9711,
          "amount": 0.0,
          "turnover": 0.0,
          "volume_ratio": 0.0,
          "amplitude": 0.0,
          "speed": 0.0,
          "change_5m": 0.0,
          "market_cap_float": 0.0,
          "market_cap_total": 0.0,
          "high": 7.61,
          "low": 7.17,
          "open": 7.27,
          "prev_close": 6.92
        },
        {
          "code": "000759",
          "name": "中百集团",
          "price": 5.52,
          "pct": 9.9602,
          "amount": 0.0,
          "turnover": 0.0,
          "volume_ratio": 0.0,
          "amplitude": 0.0,
          "speed": 0.0,
          "change_5m": 0.0,
          "market_cap_float": 0.0,
          "market_cap_total": 0.0,
          "high": 5.52,
          "low": 4.95,
          "open": 5.0,
          "prev_close": 5.02
        },
        {
          "code": "600162",
          "name": "香江控股",
          "price": 2.1,
          "pct": 9.9476,
          "amount": 0.0,
          "turnover": 0.0,
          "volume_ratio": 0.0,
          "amplitude": 0.0,
          "speed": 0.0,
          "change_5m": 0.0,
          "market_cap_float": 0.0,
          "market_cap_total": 0.0,
          "high": 2.1,
          "low": 2.1,
          "open": 2.1,
          "prev_close": 1.91
        },
        {
          "code": "600173",
          "name": "卧龙新能",
          "price": 7.41,
          "pct": 9.9407,
          "amount": 0.0,
          "turnover": 0.0,
          "volume_ratio": 0.0,
          "amplitude": 0.0,
          "speed": 0.0,
          "change_5m": 0.0,
          "market_cap_float": 0.0,
          "market_cap_total": 0.0,
          "high": 7.41,
          "low": 6.7,
          "open": 6.74,
          "prev_close": 6.74
        },
        {
          "code": "000725",
          "name": "京东方Ａ",
          "price": 5.714,
          "pct": 9.5896,
          "amount": 0.0,
          "turnover": 0.0,
          "volume_ratio": 0.0,
          "amplitude": 0.0,
          "speed": 0.0,
          "change_5m": 0.0,
          "market_cap_float": 0.0,
          "market_cap_total": 0.0,
          "high": 5.744,
          "low": 5.124,
          "open": 5.164,
          "prev_close": 5.214
        },
        {
          "code": "001225",
          "name": "和泰机电",
          "price": 62.988,
          "pct": 9.1874,
          "amount": 0.0,
          "turnover": 0.0,
          "volume_ratio": 0.0,
          "amplitude": 0.0,
          "speed": 0.0,
          "change_5m": 0.0,
          "market_cap_float": 0.0,
          "market_cap_total": 0.0,
          "high": 63.488,
          "low": 55.388,
          "open": 57.158,
          "prev_close": 57.688
        },
        {
          "code": "600590",
          "name": "泰豪科技",
          "price": 15.28,
          "pct": 8.9095,
          "amount": 0.0,
          "turnover": 0.0,
          "volume_ratio": 0.0,
          "amplitude": 0.0,
          "speed": 0.0,
          "change_5m": 0.0,
          "market_cap_float": 0.0,
          "market_cap_total": 0.0,
          "high": 15.43,
          "low": 13.11,
          "open": 13.33,
          "prev_close": 14.03
        },
        {
          "code": "002463",
          "name": "沪电股份",
          "price": 133.36,
          "pct": 8.8298,
          "amount": 0.0,
          "turnover": 0.0,
          "volume_ratio": 0.0,
          "amplitude": 0.0,
          "speed": 0.0,
          "change_5m": 0.0,
          "market_cap_float": 0.0,
          "market_cap_total": 0.0,
          "high": 134.79,
          "low": 122.55,
          "open": 122.9,
          "prev_close": 122.54
        },
        {
          "code": "600219",
          "name": "南山铝业",
          "price": 5.68,
          "pct": 8.8123,
          "amount": 0.0,
          "turnover": 0.0,
          "volume_ratio": 0.0,
          "amplitude": 0.0,
          "speed": 0.0,
          "change_5m": 0.0,
          "market_cap_float": 0.0,
          "market_cap_total": 0.0,
          "high": 5.74,
          "low": 5.23,
          "open": 5.3,
          "prev_close": 5.22
        }
      ],
      "top_amount": [
        {
          "code": "000001",
          "name": "平安银行",
          "price": 10.43,
          "pct": 1.07,
          "amount": 900879538.05,
          "turnover": 0.43,
          "volume_ratio": 0.0,
          "amplitude": 1.65,
          "speed": 0.0,
          "change_5m": 0.0,
          "market_cap_float": 0.0,
          "market_cap_total": 0.0,
          "high": 10.47,
          "low": 10.3,
          "open": 10.35,
          "prev_close": 10.32
        },
        {
          "code": "000002",
          "name": "万  科Ａ",
          "price": 3.39,
          "pct": -2.87,
          "amount": 430589235.86,
          "turnover": 1.3,
          "volume_ratio": 0.0,
          "amplitude": 3.44,
          "speed": 0.0,
          "change_5m": 0.0,
          "market_cap_float": 0.0,
          "market_cap_total": 0.0,
          "high": 3.48,
          "low": 3.36,
          "open": 3.46,
          "prev_close": 3.49
        },
        {
          "code": "000006",
          "name": "深振业Ａ",
          "price": 10.26,
          "pct": -1.5355,
          "amount": 0.0,
          "turnover": 0.0,
          "volume_ratio": 0.0,
          "amplitude": 0.0,
          "speed": 0.0,
          "change_5m": 0.0,
          "market_cap_float": 0.0,
          "market_cap_total": 0.0,
          "high": 10.43,
          "low": 9.92,
          "open": 10.34,
          "prev_close": 10.42
        },
        {
          "code": "000007",
          "name": "全新好",
          "price": 12.23,
          "pct": -2.8594,
          "amount": 0.0,
          "turnover": 0.0,
          "volume_ratio": 0.0,
          "amplitude": 0.0,
          "speed": 0.0,
          "change_5m": 0.0,
          "market_cap_float": 0.0,
          "market_cap_total": 0.0,
          "high": 12.59,
          "low": 12.05,
          "open": 12.39,
          "prev_close": 12.59
        },
        {
          "code": "000008",
          "name": "神州高铁",
          "price": 2.57,
          "pct": -1.5326,
          "amount": 0.0,
          "turnover": 0.0,
          "volume_ratio": 0.0,
          "amplitude": 0.0,
          "speed": 0.0,
          "change_5m": 0.0,
          "market_cap_float": 0.0,
          "market_cap_total": 0.0,
          "high": 2.61,
          "low": 2.56,
          "open": 2.6,
          "prev_close": 2.61
        },
        {
          "code": "000009",
          "name": "中国宝安",
          "price": 7.57,
          "pct": 0.3979,
          "amount": 0.0,
          "turnover": 0.0,
          "volume_ratio": 0.0,
          "amplitude": 0.0,
          "speed": 0.0,
          "change_5m": 0.0,
          "market_cap_float": 0.0,
          "market_cap_total": 0.0,
          "high": 7.59,
          "low": 7.46,
          "open": 7.51,
          "prev_close": 7.54
        },
        {
          "code": "000011",
          "name": "深物业A",
          "price": 7.34,
          "pct": -1.7403,
          "amount": 0.0,
          "turnover": 0.0,
          "volume_ratio": 0.0,
          "amplitude": 0.0,
          "speed": 0.0,
          "change_5m": 0.0,
          "market_cap_float": 0.0,
          "market_cap_total": 0.0,
          "high": 7.47,
          "low": 7.28,
          "open": 7.43,
          "prev_close": 7.47
        },
        {
          "code": "000012",
          "name": "南 玻Ａ",
          "price": 4.5,
          "pct": -2.1739,
          "amount": 0.0,
          "turnover": 0.0,
          "volume_ratio": 0.0,
          "amplitude": 0.0,
          "speed": 0.0,
          "change_5m": 0.0,
          "market_cap_float": 0.0,
          "market_cap_total": 0.0,
          "high": 4.73,
          "low": 4.36,
          "open": 4.37,
          "prev_close": 4.6
        },
        {
          "code": "000014",
          "name": "沙河股份",
          "price": 10.9,
          "pct": -2.5045,
          "amount": 0.0,
          "turnover": 0.0,
          "volume_ratio": 0.0,
          "amplitude": 0.0,
          "speed": 0.0,
          "change_5m": 0.0,
          "market_cap_float": 0.0,
          "market_cap_total": 0.0,
          "high": 11.18,
          "low": 10.78,
          "open": 11.1,
          "prev_close": 11.18
        },
        {
          "code": "000017",
          "name": "深中华A",
          "price": 5.56,
          "pct": -1.5929,
          "amount": 0.0,
          "turnover": 0.0,
          "volume_ratio": 0.0,
          "amplitude": 0.0,
          "speed": 0.0,
          "change_5m": 0.0,
          "market_cap_float": 0.0,
          "market_cap_total": 0.0,
          "high": 5.65,
          "low": 5.47,
          "open": 5.62,
          "prev_close": 5.65
        },
        {
          "code": "000019",
          "name": "深粮控股",
          "price": 6.54,
          "pct": -1.059,
          "amount": 0.0,
          "turnover": 0.0,
          "volume_ratio": 0.0,
          "amplitude": 0.0,
          "speed": 0.0,
          "change_5m": 0.0,
          "market_cap_float": 0.0,
          "market_cap_total": 0.0,
          "high": 6.61,
          "low": 6.45,
          "open": 6.6,
          "prev_close": 6.61
        },
        {
          "code": "000020",
          "name": "深华发Ａ",
          "price": 12.97,
          "pct": -0.077,
          "amount": 0.0,
          "turnover": 0.0,
          "volume_ratio": 0.0,
          "amplitude": 0.0,
          "speed": 0.0,
          "change_5m": 0.0,
          "market_cap_float": 0.0,
          "market_cap_total": 0.0,
          "high": 13.03,
          "low": 12.71,
          "open": 12.87,
          "prev_close": 12.98
        },
        {
          "code": "000021",
          "name": "深科技",
          "price": 42.53,
          "pct": 3.9091,
          "amount": 0.0,
          "turnover": 0.0,
          "volume_ratio": 0.0,
          "amplitude": 0.0,
          "speed": 0.0,
          "change_5m": 0.0,
          "market_cap_float": 0.0,
          "market_cap_total": 0.0,
          "high": 44.91,
          "low": 38.49,
          "open": 41.28,
          "prev_close": 40.93
        },
        {
          "code": "000025",
          "name": "特 力Ａ",
          "price": 14.62,
          "pct": -0.6118,
          "amount": 0.0,
          "turnover": 0.0,
          "volume_ratio": 0.0,
          "amplitude": 0.0,
          "speed": 0.0,
          "change_5m": 0.0,
          "market_cap_float": 0.0,
          "market_cap_total": 0.0,
          "high": 14.71,
          "low": 14.36,
          "open": 14.66,
          "prev_close": 14.71
        },
        {
          "code": "000026",
          "name": "飞亚达",
          "price": 24.22,
          "pct": -10.0297,
          "amount": 0.0,
          "turnover": 0.0,
          "volume_ratio": 0.0,
          "amplitude": 0.0,
          "speed": 0.0,
          "change_5m": 0.0,
          "market_cap_float": 0.0,
          "market_cap_total": 0.0,
          "high": 25.47,
          "low": 24.22,
          "open": 25.13,
          "prev_close": 26.92
        },
        {
          "code": "000027",
          "name": "深圳能源",
          "price": 7.62,
          "pct": 0.7937,
          "amount": 0.0,
          "turnover": 0.0,
          "volume_ratio": 0.0,
          "amplitude": 0.0,
          "speed": 0.0,
          "change_5m": 0.0,
          "market_cap_float": 0.0,
          "market_cap_total": 0.0,
          "high": 7.7,
          "low": 7.37,
          "open": 7.49,
          "prev_close": 7.56
        },
        {
          "code": "000028",
          "name": "国药一致",
          "price": 23.58,
          "pct": -0.5063,
          "amount": 0.0,
          "turnover": 0.0,
          "volume_ratio": 0.0,
          "amplitude": 0.0,
          "speed": 0.0,
          "change_5m": 0.0,
          "market_cap_float": 0.0,
          "market_cap_total": 0.0,
          "high": 23.73,
          "low": 23.49,
          "open": 23.73,
          "prev_close": 23.7
        },
        {
          "code": "000029",
          "name": "深深房Ａ",
          "price": 24.915,
          "pct": 0.7277,
          "amount": 0.0,
          "turnover": 0.0,
          "volume_ratio": 0.0,
          "amplitude": 0.0,
          "speed": 0.0,
          "change_5m": 0.0,
          "market_cap_float": 0.0,
          "market_cap_total": 0.0,
          "high": 25.245,
          "low": 24.325,
          "open": 24.775,
          "prev_close": 24.735
        },
        {
          "code": "000030",
          "name": "富奥股份",
          "price": 4.75,
          "pct": -0.2101,
          "amount": 0.0,
          "turnover": 0.0,
          "volume_ratio": 0.0,
          "amplitude": 0.0,
          "speed": 0.0,
          "change_5m": 0.0,
          "market_cap_float": 0.0,
          "market_cap_total": 0.0,
          "high": 4.77,
          "low": 4.69,
          "open": 4.74,
          "prev_close": 4.76
        },
        {
          "code": "000031",
          "name": "大悦城",
          "price": 2.59,
          "pct": -2.6316,
          "amount": 0.0,
          "turnover": 0.0,
          "volume_ratio": 0.0,
          "amplitude": 0.0,
          "speed": 0.0,
          "change_5m": 0.0,
          "market_cap_float": 0.0,
          "market_cap_total": 0.0,
          "high": 2.67,
          "low": 2.56,
          "open": 2.66,
          "prev_close": 2.66
        },
        {
          "code": "000032",
          "name": "深桑达Ａ",
          "price": 18.285,
          "pct": -3.1258,
          "amount": 0.0,
          "turnover": 0.0,
          "volume_ratio": 0.0,
          "amplitude": 0.0,
          "speed": 0.0,
          "change_5m": 0.0,
          "market_cap_float": 0.0,
          "market_cap_total": 0.0,
          "high": 18.765,
          "low": 17.845,
          "open": 18.745,
          "prev_close": 18.875
        },
        {
          "code": "000034",
          "name": "神州数码",
          "price": 27.87,
          "pct": -5.5894,
          "amount": 0.0,
          "turnover": 0.0,
          "volume_ratio": 0.0,
          "amplitude": 0.0,
          "speed": 0.0,
          "change_5m": 0.0,
          "market_cap_float": 0.0,
          "market_cap_total": 0.0,
          "high": 29.2,
          "low": 27.43,
          "open": 29.2,
          "prev_close": 29.52
        },
        {
          "code": "000035",
          "name": "中国天楹",
          "price": 6.08,
          "pct": 2.5295,
          "amount": 0.0,
          "turnover": 0.0,
          "volume_ratio": 0.0,
          "amplitude": 0.0,
          "speed": 0.0,
          "change_5m": 0.0,
          "market_cap_float": 0.0,
          "market_cap_total": 0.0,
          "high": 6.11,
          "low": 5.81,
          "open": 5.93,
          "prev_close": 5.93
        },
        {
          "code": "000036",
          "name": "华联控股",
          "price": 5.39,
          "pct": 0.1859,
          "amount": 0.0,
          "turnover": 0.0,
          "volume_ratio": 0.0,
          "amplitude": 0.0,
          "speed": 0.0,
          "change_5m": 0.0,
          "market_cap_float": 0.0,
          "market_cap_total": 0.0,
          "high": 5.51,
          "low": 5.3,
          "open": 5.36,
          "prev_close": 5.38
        },
        {
          "code": "000037",
          "name": "深南电A",
          "price": 9.88,
          "pct": -1.2,
          "amount": 0.0,
          "turnover": 0.0,
          "volume_ratio": 0.0,
          "amplitude": 0.0,
          "speed": 0.0,
          "change_5m": 0.0,
          "market_cap_float": 0.0,
          "market_cap_total": 0.0,
          "high": 10.06,
          "low": 9.62,
          "open": 10.01,
          "prev_close": 10.0
        },
        {
          "code": "000039",
          "name": "中集集团",
          "price": 10.11,
          "pct": -0.0988,
          "amount": 0.0,
          "turnover": 0.0,
          "volume_ratio": 0.0,
          "amplitude": 0.0,
          "speed": 0.0,
          "change_5m": 0.0,
          "market_cap_float": 0.0,
          "market_cap_total": 0.0,
          "high": 10.18,
          "low": 9.8,
          "open": 10.13,
          "prev_close": 10.12
        },
        {
          "code": "000042",
          "name": "中洲控股",
          "price": 9.94,
          "pct": -1.9724,
          "amount": 0.0,
          "turnover": 0.0,
          "volume_ratio": 0.0,
          "amplitude": 0.0,
          "speed": 0.0,
          "change_5m": 0.0,
          "market_cap_float": 0.0,
          "market_cap_total": 0.0,
          "high": 10.14,
          "low": 9.64,
          "open": 10.14,
          "prev_close": 10.14
        },
        {
          "code": "000045",
          "name": "深纺织Ａ",
          "price": 12.012,
          "pct": -0.0832,
          "amount": 0.0,
          "turnover": 0.0,
          "volume_ratio": 0.0,
          "amplitude": 0.0,
          "speed": 0.0,
          "change_5m": 0.0,
          "market_cap_float": 0.0,
          "market_cap_total": 0.0,
          "high": 12.192,
          "low": 11.842,
          "open": 11.982,
          "prev_close": 12.022
        },
        {
          "code": "000048",
          "name": "京基智农",
          "price": 13.28,
          "pct": -1.0432,
          "amount": 0.0,
          "turnover": 0.0,
          "volume_ratio": 0.0,
          "amplitude": 0.0,
          "speed": 0.0,
          "change_5m": 0.0,
          "market_cap_float": 0.0,
          "market_cap_total": 0.0,
          "high": 13.45,
          "low": 13.1,
          "open": 13.44,
          "prev_close": 13.42
        },
        {
          "code": "000049",
          "name": "德赛电池",
          "price": 26.33,
          "pct": -1.2378,
          "amount": 0.0,
          "turnover": 0.0,
          "volume_ratio": 0.0,
          "amplitude": 0.0,
          "speed": 0.0,
          "change_5m": 0.0,
          "market_cap_float": 0.0,
          "market_cap_total": 0.0,
          "high": 26.74,
          "low": 25.97,
          "open": 26.6,
          "prev_close": 26.66
        },
        {
          "code": "000050",
          "name": "深天马Ａ",
          "price": 8.27,
          "pct": 2.6055,
          "amount": 0.0,
          "turnover": 0.0,
          "volume_ratio": 0.0,
          "amplitude": 0.0,
          "speed": 0.0,
          "change_5m": 0.0,
          "market_cap_float": 0.0,
          "market_cap_total": 0.0,
          "high": 8.4,
          "low": 7.94,
          "open": 7.98,
          "prev_close": 8.06
        },
        {
          "code": "000055",
          "name": "方大集团",
          "price": 3.48,
          "pct": -2.521,
          "amount": 0.0,
          "turnover": 0.0,
          "volume_ratio": 0.0,
          "amplitude": 0.0,
          "speed": 0.0,
          "change_5m": 0.0,
          "market_cap_float": 0.0,
          "market_cap_total": 0.0,
          "high": 3.58,
          "low": 3.44,
          "open": 3.57,
          "prev_close": 3.57
        },
        {
          "code": "000058",
          "name": "深 赛 格",
          "price": 7.326,
          "pct": -2.6575,
          "amount": 0.0,
          "turnover": 0.0,
          "volume_ratio": 0.0,
          "amplitude": 0.0,
          "speed": 0.0,
          "change_5m": 0.0,
          "market_cap_float": 0.0,
          "market_cap_total": 0.0,
          "high": 7.536,
          "low": 7.216,
          "open": 7.506,
          "prev_close": 7.526
        },
        {
          "code": "000059",
          "name": "华锦股份",
          "price": 4.57,
          "pct": -0.2183,
          "amount": 0.0,
          "turnover": 0.0,
          "volume_ratio": 0.0,
          "amplitude": 0.0,
          "speed": 0.0,
          "change_5m": 0.0,
          "market_cap_float": 0.0,
          "market_cap_total": 0.0,
          "high": 4.59,
          "low": 4.51,
          "open": 4.57,
          "prev_close": 4.58
        },
        {
          "code": "000060",
          "name": "中金岭南",
          "price": 7.9,
          "pct": 2.5974,
          "amount": 0.0,
          "turnover": 0.0,
          "volume_ratio": 0.0,
          "amplitude": 0.0,
          "speed": 0.0,
          "change_5m": 0.0,
          "market_cap_float": 0.0,
          "market_cap_total": 0.0,
          "high": 8.02,
          "low": 7.43,
          "open": 7.69,
          "prev_close": 7.7
        },
        {
          "code": "000061",
          "name": "农 产 品",
          "price": 6.55,
          "pct": -0.1524,
          "amount": 0.0,
          "turnover": 0.0,
          "volume_ratio": 0.0,
          "amplitude": 0.0,
          "speed": 0.0,
          "change_5m": 0.0,
          "market_cap_float": 0.0,
          "market_cap_total": 0.0,
          "high": 6.65,
          "low": 6.48,
          "open": 6.53,
          "prev_close": 6.56
        },
        {
          "code": "000062",
          "name": "深圳华强",
          "price": 33.66,
          "pct": -6.9652,
          "amount": 0.0,
          "turnover": 0.0,
          "volume_ratio": 0.0,
          "amplitude": 0.0,
          "speed": 0.0,
          "change_5m": 0.0,
          "market_cap_float": 0.0,
          "market_cap_total": 0.0,
          "high": 35.09,
          "low": 33.29,
          "open": 34.82,
          "prev_close": 36.18
        },
        {
          "code": "000063",
          "name": "中兴通讯",
          "price": 35.54,
          "pct": -2.0127,
          "amount": 0.0,
          "turnover": 0.0,
          "volume_ratio": 0.0,
          "amplitude": 0.0,
          "speed": 0.0,
          "change_5m": 0.0,
          "market_cap_float": 0.0,
          "market_cap_total": 0.0,
          "high": 36.0,
          "low": 34.77,
          "open": 36.0,
          "prev_close": 36.27
        },
        {
          "code": "000065",
          "name": "北方国际",
          "price": 12.383,
          "pct": -4.1786,
          "amount": 0.0,
          "turnover": 0.0,
          "volume_ratio": 0.0,
          "amplitude": 0.0,
          "speed": 0.0,
          "change_5m": 0.0,
          "market_cap_float": 0.0,
          "market_cap_total": 0.0,
          "high": 12.583,
          "low": 12.213,
          "open": 12.503,
          "prev_close": 12.923
        },
        {
          "code": "000066",
          "name": "中国长城",
          "price": 19.3,
          "pct": -6.2196,
          "amount": 0.0,
          "turnover": 0.0,
          "volume_ratio": 0.0,
          "amplitude": 0.0,
          "speed": 0.0,
          "change_5m": 0.0,
          "market_cap_float": 0.0,
          "market_cap_total": 0.0,
          "high": 20.0,
          "low": 18.9,
          "open": 20.0,
          "prev_close": 20.58
        },
        {
          "code": "000068",
          "name": "华控赛格",
          "price": 3.01,
          "pct": -2.9032,
          "amount": 0.0,
          "turnover": 0.0,
          "volume_ratio": 0.0,
          "amplitude": 0.0,
          "speed": 0.0,
          "change_5m": 0.0,
          "market_cap_float": 0.0,
          "market_cap_total": 0.0,
          "high": 3.09,
          "low": 2.95,
          "open": 3.09,
          "prev_close": 3.1
        },
        {
          "code": "000069",
          "name": "华侨城Ａ",
          "price": 1.96,
          "pct": -0.5076,
          "amount": 0.0,
          "turnover": 0.0,
          "volume_ratio": 0.0,
          "amplitude": 0.0,
          "speed": 0.0,
          "change_5m": 0.0,
          "market_cap_float": 0.0,
          "market_cap_total": 0.0,
          "high": 1.98,
          "low": 1.93,
          "open": 1.96,
          "prev_close": 1.97
        },
        {
          "code": "000070",
          "name": "特发信息",
          "price": 17.43,
          "pct": -4.8581,
          "amount": 0.0,
          "turnover": 0.0,
          "volume_ratio": 0.0,
          "amplitude": 0.0,
          "speed": 0.0,
          "change_5m": 0.0,
          "market_cap_float": 0.0,
          "market_cap_total": 0.0,
          "high": 18.18,
          "low": 16.88,
          "open": 18.14,
          "prev_close": 18.32
        },
        {
          "code": "000088",
          "name": "盐 田 港",
          "price": 4.5,
          "pct": 0.4464,
          "amount": 0.0,
          "turnover": 0.0,
          "volume_ratio": 0.0,
          "amplitude": 0.0,
          "speed": 0.0,
          "change_5m": 0.0,
          "market_cap_float": 0.0,
          "market_cap_total": 0.0,
          "high": 4.5,
          "low": 4.45,
          "open": 4.47,
          "prev_close": 4.48
        },
        {
          "code": "000089",
          "name": "深圳机场",
          "price": 6.82,
          "pct": 0.59,
          "amount": 0.0,
          "turnover": 0.0,
          "volume_ratio": 0.0,
          "amplitude": 0.0,
          "speed": 0.0,
          "change_5m": 0.0,
          "market_cap_float": 0.0,
          "market_cap_total": 0.0,
          "high": 6.83,
          "low": 6.74,
          "open": 6.76,
          "prev_close": 6.78
        },
        {
          "code": "000090",
          "name": "天健集团",
          "price": 3.28,
          "pct": -1.5015,
          "amount": 0.0,
          "turnover": 0.0,
          "volume_ratio": 0.0,
          "amplitude": 0.0,
          "speed": 0.0,
          "change_5m": 0.0,
          "market_cap_float": 0.0,
          "market_cap_total": 0.0,
          "high": 3.32,
          "low": 3.26,
          "open": 3.31,
          "prev_close": 3.33
        },
        {
          "code": "000096",
          "name": "广聚能源",
          "price": 8.35,
          "pct": -1.1834,
          "amount": 0.0,
          "turnover": 0.0,
          "volume_ratio": 0.0,
          "amplitude": 0.0,
          "speed": 0.0,
          "change_5m": 0.0,
          "market_cap_float": 0.0,
          "market_cap_total": 0.0,
          "high": 8.43,
          "low": 8.24,
          "open": 8.43,
          "prev_close": 8.45
        },
        {
          "code": "000099",
          "name": "中信海直",
          "price": 16.56,
          "pct": -1.5458,
          "amount": 0.0,
          "turnover": 0.0,
          "volume_ratio": 0.0,
          "amplitude": 0.0,
          "speed": 0.0,
          "change_5m": 0.0,
          "market_cap_float": 0.0,
          "market_cap_total": 0.0,
          "high": 16.84,
          "low": 16.35,
          "open": 16.7,
          "prev_close": 16.82
        },
        {
          "code": "000100",
          "name": "TCL科技",
          "price": 4.56,
          "pct": 4.8276,
          "amount": 0.0,
          "turnover": 0.0,
          "volume_ratio": 0.0,
          "amplitude": 0.0,
          "speed": 0.0,
          "change_5m": 0.0,
          "market_cap_float": 0.0,
          "market_cap_total": 0.0,
          "high": 4.64,
          "low": 4.28,
          "open": 4.29,
          "prev_close": 4.35
        },
        {
          "code": "000151",
          "name": "中成股份",
          "price": 11.31,
          "pct": -1.9081,
          "amount": 0.0,
          "turnover": 0.0,
          "volume_ratio": 0.0,
          "amplitude": 0.0,
          "speed": 0.0,
          "change_5m": 0.0,
          "market_cap_float": 0.0,
          "market_cap_total": 0.0,
          "high": 11.51,
          "low": 11.15,
          "open": 11.46,
          "prev_close": 11.53
        }
      ],
      "top_turnover": [
        {
          "code": "000002",
          "name": "万  科Ａ",
          "price": 3.39,
          "pct": -2.87,
          "amount": 430589235.86,
          "turnover": 1.3,
          "volume_ratio": 0.0,
          "amplitude": 3.44,
          "speed": 0.0,
          "change_5m": 0.0,
          "market_cap_float": 0.0,
          "market_cap_total": 0.0,
          "high": 3.48,
          "low": 3.36,
          "open": 3.46,
          "prev_close": 3.49
        },
        {
          "code": "000001",
          "name": "平安银行",
          "price": 10.43,
          "pct": 1.07,
          "amount": 900879538.05,
          "turnover": 0.43,
          "volume_ratio": 0.0,
          "amplitude": 1.65,
          "speed": 0.0,
          "change_5m": 0.0,
          "market_cap_float": 0.0,
          "market_cap_total": 0.0,
          "high": 10.47,
          "low": 10.3,
          "open": 10.35,
          "prev_close": 10.32
        },
        {
          "code": "000006",
          "name": "深振业Ａ",
          "price": 10.26,
          "pct": -1.5355,
          "amount": 0.0,
          "turnover": 0.0,
          "volume_ratio": 0.0,
          "amplitude": 0.0,
          "speed": 0.0,
          "change_5m": 0.0,
          "market_cap_float": 0.0,
          "market_cap_total": 0.0,
          "high": 10.43,
          "low": 9.92,
          "open": 10.34,
          "prev_close": 10.42
        },
        {
          "code": "000007",
          "name": "全新好",
          "price": 12.23,
          "pct": -2.8594,
          "amount": 0.0,
          "turnover": 0.0,
          "volume_ratio": 0.0,
          "amplitude": 0.0,
          "speed": 0.0,
          "change_5m": 0.0,
          "market_cap_float": 0.0,
          "market_cap_total": 0.0,
          "high": 12.59,
          "low": 12.05,
          "open": 12.39,
          "prev_close": 12.59
        },
        {
          "code": "000008",
          "name": "神州高铁",
          "price": 2.57,
          "pct": -1.5326,
          "amount": 0.0,
          "turnover": 0.0,
          "volume_ratio": 0.0,
          "amplitude": 0.0,
          "speed": 0.0,
          "change_5m": 0.0,
          "market_cap_float": 0.0,
          "market_cap_total": 0.0,
          "high": 2.61,
          "low": 2.56,
          "open": 2.6,
          "prev_close": 2.61
        },
        {
          "code": "000009",
          "name": "中国宝安",
          "price": 7.57,
          "pct": 0.3979,
          "amount": 0.0,
          "turnover": 0.0,
          "volume_ratio": 0.0,
          "amplitude": 0.0,
          "speed": 0.0,
          "change_5m": 0.0,
          "market_cap_float": 0.0,
          "market_cap_total": 0.0,
          "high": 7.59,
          "low": 7.46,
          "open": 7.51,
          "prev_close": 7.54
        },
        {
          "code": "000011",
          "name": "深物业A",
          "price": 7.34,
          "pct": -1.7403,
          "amount": 0.0,
          "turnover": 0.0,
          "volume_ratio": 0.0,
          "amplitude": 0.0,
          "speed": 0.0,
          "change_5m": 0.0,
          "market_cap_float": 0.0,
          "market_cap_total": 0.0,
          "high": 7.47,
          "low": 7.28,
          "open": 7.43,
          "prev_close": 7.47
        },
        {
          "code": "000012",
          "name": "南 玻Ａ",
          "price": 4.5,
          "pct": -2.1739,
          "amount": 0.0,
          "turnover": 0.0,
          "volume_ratio": 0.0,
          "amplitude": 0.0,
          "speed": 0.0,
          "change_5m": 0.0,
          "market_cap_float": 0.0,
          "market_cap_total": 0.0,
          "high": 4.73,
          "low": 4.36,
          "open": 4.37,
          "prev_close": 4.6
        },
        {
          "code": "000014",
          "name": "沙河股份",
          "price": 10.9,
          "pct": -2.5045,
          "amount": 0.0,
          "turnover": 0.0,
          "volume_ratio": 0.0,
          "amplitude": 0.0,
          "speed": 0.0,
          "change_5m": 0.0,
          "market_cap_float": 0.0,
          "market_cap_total": 0.0,
          "high": 11.18,
          "low": 10.78,
          "open": 11.1,
          "prev_close": 11.18
        },
        {
          "code": "000017",
          "name": "深中华A",
          "price": 5.56,
          "pct": -1.5929,
          "amount": 0.0,
          "turnover": 0.0,
          "volume_ratio": 0.0,
          "amplitude": 0.0,
          "speed": 0.0,
          "change_5m": 0.0,
          "market_cap_float": 0.0,
          "market_cap_total": 0.0,
          "high": 5.65,
          "low": 5.47,
          "open": 5.62,
          "prev_close": 5.65
        },
        {
          "code": "000019",
          "name": "深粮控股",
          "price": 6.54,
          "pct": -1.059,
          "amount": 0.0,
          "turnover": 0.0,
          "volume_ratio": 0.0,
          "amplitude": 0.0,
          "speed": 0.0,
          "change_5m": 0.0,
          "market_cap_float": 0.0,
          "market_cap_total": 0.0,
          "high": 6.61,
          "low": 6.45,
          "open": 6.6,
          "prev_close": 6.61
        },
        {
          "code": "000020",
          "name": "深华发Ａ",
          "price": 12.97,
          "pct": -0.077,
          "amount": 0.0,
          "turnover": 0.0,
          "volume_ratio": 0.0,
          "amplitude": 0.0,
          "speed": 0.0,
          "change_5m": 0.0,
          "market_cap_float": 0.0,
          "market_cap_total": 0.0,
          "high": 13.03,
          "low": 12.71,
          "open": 12.87,
          "prev_close": 12.98
        },
        {
          "code": "000021",
          "name": "深科技",
          "price": 42.53,
          "pct": 3.9091,
          "amount": 0.0,
          "turnover": 0.0,
          "volume_ratio": 0.0,
          "amplitude": 0.0,
          "speed": 0.0,
          "change_5m": 0.0,
          "market_cap_float": 0.0,
          "market_cap_total": 0.0,
          "high": 44.91,
          "low": 38.49,
          "open": 41.28,
          "prev_close": 40.93
        },
        {
          "code": "000025",
          "name": "特 力Ａ",
          "price": 14.62,
          "pct": -0.6118,
          "amount": 0.0,
          "turnover": 0.0,
          "volume_ratio": 0.0,
          "amplitude": 0.0,
          "speed": 0.0,
          "change_5m": 0.0,
          "market_cap_float": 0.0,
          "market_cap_total": 0.0,
          "high": 14.71,
          "low": 14.36,
          "open": 14.66,
          "prev_close": 14.71
        },
        {
          "code": "000026",
          "name": "飞亚达",
          "price": 24.22,
          "pct": -10.0297,
          "amount": 0.0,
          "turnover": 0.0,
          "volume_ratio": 0.0,
          "amplitude": 0.0,
          "speed": 0.0,
          "change_5m": 0.0,
          "market_cap_float": 0.0,
          "market_cap_total": 0.0,
          "high": 25.47,
          "low": 24.22,
          "open": 25.13,
          "prev_close": 26.92
        },
        {
          "code": "000027",
          "name": "深圳能源",
          "price": 7.62,
          "pct": 0.7937,
          "amount": 0.0,
          "turnover": 0.0,
          "volume_ratio": 0.0,
          "amplitude": 0.0,
          "speed": 0.0,
          "change_5m": 0.0,
          "market_cap_float": 0.0,
          "market_cap_total": 0.0,
          "high": 7.7,
          "low": 7.37,
          "open": 7.49,
          "prev_close": 7.56
        },
        {
          "code": "000028",
          "name": "国药一致",
          "price": 23.58,
          "pct": -0.5063,
          "amount": 0.0,
          "turnover": 0.0,
          "volume_ratio": 0.0,
          "amplitude": 0.0,
          "speed": 0.0,
          "change_5m": 0.0,
          "market_cap_float": 0.0,
          "market_cap_total": 0.0,
          "high": 23.73,
          "low": 23.49,
          "open": 23.73,
          "prev_close": 23.7
        },
        {
          "code": "000029",
          "name": "深深房Ａ",
          "price": 24.915,
          "pct": 0.7277,
          "amount": 0.0,
          "turnover": 0.0,
          "volume_ratio": 0.0,
          "amplitude": 0.0,
          "speed": 0.0,
          "change_5m": 0.0,
          "market_cap_float": 0.0,
          "market_cap_total": 0.0,
          "high": 25.245,
          "low": 24.325,
          "open": 24.775,
          "prev_close": 24.735
        },
        {
          "code": "000030",
          "name": "富奥股份",
          "price": 4.75,
          "pct": -0.2101,
          "amount": 0.0,
          "turnover": 0.0,
          "volume_ratio": 0.0,
          "amplitude": 0.0,
          "speed": 0.0,
          "change_5m": 0.0,
          "market_cap_float": 0.0,
          "market_cap_total": 0.0,
          "high": 4.77,
          "low": 4.69,
          "open": 4.74,
          "prev_close": 4.76
        },
        {
          "code": "000031",
          "name": "大悦城",
          "price": 2.59,
          "pct": -2.6316,
          "amount": 0.0,
          "turnover": 0.0,
          "volume_ratio": 0.0,
          "amplitude": 0.0,
          "speed": 0.0,
          "change_5m": 0.0,
          "market_cap_float": 0.0,
          "market_cap_total": 0.0,
          "high": 2.67,
          "low": 2.56,
          "open": 2.66,
          "prev_close": 2.66
        },
        {
          "code": "000032",
          "name": "深桑达Ａ",
          "price": 18.285,
          "pct": -3.1258,
          "amount": 0.0,
          "turnover": 0.0,
          "volume_ratio": 0.0,
          "amplitude": 0.0,
          "speed": 0.0,
          "change_5m": 0.0,
          "market_cap_float": 0.0,
          "market_cap_total": 0.0,
          "high": 18.765,
          "low": 17.845,
          "open": 18.745,
          "prev_close": 18.875
        },
        {
          "code": "000034",
          "name": "神州数码",
          "price": 27.87,
          "pct": -5.5894,
          "amount": 0.0,
          "turnover": 0.0,
          "volume_ratio": 0.0,
          "amplitude": 0.0,
          "speed": 0.0,
          "change_5m": 0.0,
          "market_cap_float": 0.0,
          "market_cap_total": 0.0,
          "high": 29.2,
          "low": 27.43,
          "open": 29.2,
          "prev_close": 29.52
        },
        {
          "code": "000035",
          "name": "中国天楹",
          "price": 6.08,
          "pct": 2.5295,
          "amount": 0.0,
          "turnover": 0.0,
          "volume_ratio": 0.0,
          "amplitude": 0.0,
          "speed": 0.0,
          "change_5m": 0.0,
          "market_cap_float": 0.0,
          "market_cap_total": 0.0,
          "high": 6.11,
          "low": 5.81,
          "open": 5.93,
          "prev_close": 5.93
        },
        {
          "code": "000036",
          "name": "华联控股",
          "price": 5.39,
          "pct": 0.1859,
          "amount": 0.0,
          "turnover": 0.0,
          "volume_ratio": 0.0,
          "amplitude": 0.0,
          "speed": 0.0,
          "change_5m": 0.0,
          "market_cap_float": 0.0,
          "market_cap_total": 0.0,
          "high": 5.51,
          "low": 5.3,
          "open": 5.36,
          "prev_close": 5.38
        },
        {
          "code": "000037",
          "name": "深南电A",
          "price": 9.88,
          "pct": -1.2,
          "amount": 0.0,
          "turnover": 0.0,
          "volume_ratio": 0.0,
          "amplitude": 0.0,
          "speed": 0.0,
          "change_5m": 0.0,
          "market_cap_float": 0.0,
          "market_cap_total": 0.0,
          "high": 10.06,
          "low": 9.62,
          "open": 10.01,
          "prev_close": 10.0
        },
        {
          "code": "000039",
          "name": "中集集团",
          "price": 10.11,
          "pct": -0.0988,
          "amount": 0.0,
          "turnover": 0.0,
          "volume_ratio": 0.0,
          "amplitude": 0.0,
          "speed": 0.0,
          "change_5m": 0.0,
          "market_cap_float": 0.0,
          "market_cap_total": 0.0,
          "high": 10.18,
          "low": 9.8,
          "open": 10.13,
          "prev_close": 10.12
        },
        {
          "code": "000042",
          "name": "中洲控股",
          "price": 9.94,
          "pct": -1.9724,
          "amount": 0.0,
          "turnover": 0.0,
          "volume_ratio": 0.0,
          "amplitude": 0.0,
          "speed": 0.0,
          "change_5m": 0.0,
          "market_cap_float": 0.0,
          "market_cap_total": 0.0,
          "high": 10.14,
          "low": 9.64,
          "open": 10.14,
          "prev_close": 10.14
        },
        {
          "code": "000045",
          "name": "深纺织Ａ",
          "price": 12.012,
          "pct": -0.0832,
          "amount": 0.0,
          "turnover": 0.0,
          "volume_ratio": 0.0,
          "amplitude": 0.0,
          "speed": 0.0,
          "change_5m": 0.0,
          "market_cap_float": 0.0,
          "market_cap_total": 0.0,
          "high": 12.192,
          "low": 11.842,
          "open": 11.982,
          "prev_close": 12.022
        },
        {
          "code": "000048",
          "name": "京基智农",
          "price": 13.28,
          "pct": -1.0432,
          "amount": 0.0,
          "turnover": 0.0,
          "volume_ratio": 0.0,
          "amplitude": 0.0,
          "speed": 0.0,
          "change_5m": 0.0,
          "market_cap_float": 0.0,
          "market_cap_total": 0.0,
          "high": 13.45,
          "low": 13.1,
          "open": 13.44,
          "prev_close": 13.42
        },
        {
          "code": "000049",
          "name": "德赛电池",
          "price": 26.33,
          "pct": -1.2378,
          "amount": 0.0,
          "turnover": 0.0,
          "volume_ratio": 0.0,
          "amplitude": 0.0,
          "speed": 0.0,
          "change_5m": 0.0,
          "market_cap_float": 0.0,
          "market_cap_total": 0.0,
          "high": 26.74,
          "low": 25.97,
          "open": 26.6,
          "prev_close": 26.66
        },
        {
          "code": "000050",
          "name": "深天马Ａ",
          "price": 8.27,
          "pct": 2.6055,
          "amount": 0.0,
          "turnover": 0.0,
          "volume_ratio": 0.0,
          "amplitude": 0.0,
          "speed": 0.0,
          "change_5m": 0.0,
          "market_cap_float": 0.0,
          "market_cap_total": 0.0,
          "high": 8.4,
          "low": 7.94,
          "open": 7.98,
          "prev_close": 8.06
        },
        {
          "code": "000055",
          "name": "方大集团",
          "price": 3.48,
          "pct": -2.521,
          "amount": 0.0,
          "turnover": 0.0,
          "volume_ratio": 0.0,
          "amplitude": 0.0,
          "speed": 0.0,
          "change_5m": 0.0,
          "market_cap_float": 0.0,
          "market_cap_total": 0.0,
          "high": 3.58,
          "low": 3.44,
          "open": 3.57,
          "prev_close": 3.57
        },
        {
          "code": "000058",
          "name": "深 赛 格",
          "price": 7.326,
          "pct": -2.6575,
          "amount": 0.0,
          "turnover": 0.0,
          "volume_ratio": 0.0,
          "amplitude": 0.0,
          "speed": 0.0,
          "change_5m": 0.0,
          "market_cap_float": 0.0,
          "market_cap_total": 0.0,
          "high": 7.536,
          "low": 7.216,
          "open": 7.506,
          "prev_close": 7.526
        },
        {
          "code": "000059",
          "name": "华锦股份",
          "price": 4.57,
          "pct": -0.2183,
          "amount": 0.0,
          "turnover": 0.0,
          "volume_ratio": 0.0,
          "amplitude": 0.0,
          "speed": 0.0,
          "change_5m": 0.0,
          "market_cap_float": 0.0,
          "market_cap_total": 0.0,
          "high": 4.59,
          "low": 4.51,
          "open": 4.57,
          "prev_close": 4.58
        },
        {
          "code": "000060",
          "name": "中金岭南",
          "price": 7.9,
          "pct": 2.5974,
          "amount": 0.0,
          "turnover": 0.0,
          "volume_ratio": 0.0,
          "amplitude": 0.0,
          "speed": 0.0,
          "change_5m": 0.0,
          "market_cap_float": 0.0,
          "market_cap_total": 0.0,
          "high": 8.02,
          "low": 7.43,
          "open": 7.69,
          "prev_close": 7.7
        },
        {
          "code": "000061",
          "name": "农 产 品",
          "price": 6.55,
          "pct": -0.1524,
          "amount": 0.0,
          "turnover": 0.0,
          "volume_ratio": 0.0,
          "amplitude": 0.0,
          "speed": 0.0,
          "change_5m": 0.0,
          "market_cap_float": 0.0,
          "market_cap_total": 0.0,
          "high": 6.65,
          "low": 6.48,
          "open": 6.53,
          "prev_close": 6.56
        },
        {
          "code": "000062",
          "name": "深圳华强",
          "price": 33.66,
          "pct": -6.9652,
          "amount": 0.0,
          "turnover": 0.0,
          "volume_ratio": 0.0,
          "amplitude": 0.0,
          "speed": 0.0,
          "change_5m": 0.0,
          "market_cap_float": 0.0,
          "market_cap_total": 0.0,
          "high": 35.09,
          "low": 33.29,
          "open": 34.82,
          "prev_close": 36.18
        },
        {
          "code": "000063",
          "name": "中兴通讯",
          "price": 35.54,
          "pct": -2.0127,
          "amount": 0.0,
          "turnover": 0.0,
          "volume_ratio": 0.0,
          "amplitude": 0.0,
          "speed": 0.0,
          "change_5m": 0.0,
          "market_cap_float": 0.0,
          "market_cap_total": 0.0,
          "high": 36.0,
          "low": 34.77,
          "open": 36.0,
          "prev_close": 36.27
        },
        {
          "code": "000065",
          "name": "北方国际",
          "price": 12.383,
          "pct": -4.1786,
          "amount": 0.0,
          "turnover": 0.0,
          "volume_ratio": 0.0,
          "amplitude": 0.0,
          "speed": 0.0,
          "change_5m": 0.0,
          "market_cap_float": 0.0,
          "market_cap_total": 0.0,
          "high": 12.583,
          "low": 12.213,
          "open": 12.503,
          "prev_close": 12.923
        },
        {
          "code": "000066",
          "name": "中国长城",
          "price": 19.3,
          "pct": -6.2196,
          "amount": 0.0,
          "turnover": 0.0,
          "volume_ratio": 0.0,
          "amplitude": 0.0,
          "speed": 0.0,
          "change_5m": 0.0,
          "market_cap_float": 0.0,
          "market_cap_total": 0.0,
          "high": 20.0,
          "low": 18.9,
          "open": 20.0,
          "prev_close": 20.58
        },
        {
          "code": "000068",
          "name": "华控赛格",
          "price": 3.01,
          "pct": -2.9032,
          "amount": 0.0,
          "turnover": 0.0,
          "volume_ratio": 0.0,
          "amplitude": 0.0,
          "speed": 0.0,
          "change_5m": 0.0,
          "market_cap_float": 0.0,
          "market_cap_total": 0.0,
          "high": 3.09,
          "low": 2.95,
          "open": 3.09,
          "prev_close": 3.1
        },
        {
          "code": "000069",
          "name": "华侨城Ａ",
          "price": 1.96,
          "pct": -0.5076,
          "amount": 0.0,
          "turnover": 0.0,
          "volume_ratio": 0.0,
          "amplitude": 0.0,
          "speed": 0.0,
          "change_5m": 0.0,
          "market_cap_float": 0.0,
          "market_cap_total": 0.0,
          "high": 1.98,
          "low": 1.93,
          "open": 1.96,
          "prev_close": 1.97
        },
        {
          "code": "000070",
          "name": "特发信息",
          "price": 17.43,
          "pct": -4.8581,
          "amount": 0.0,
          "turnover": 0.0,
          "volume_ratio": 0.0,
          "amplitude": 0.0,
          "speed": 0.0,
          "change_5m": 0.0,
          "market_cap_float": 0.0,
          "market_cap_total": 0.0,
          "high": 18.18,
          "low": 16.88,
          "open": 18.14,
          "prev_close": 18.32
        },
        {
          "code": "000088",
          "name": "盐 田 港",
          "price": 4.5,
          "pct": 0.4464,
          "amount": 0.0,
          "turnover": 0.0,
          "volume_ratio": 0.0,
          "amplitude": 0.0,
          "speed": 0.0,
          "change_5m": 0.0,
          "market_cap_float": 0.0,
          "market_cap_total": 0.0,
          "high": 4.5,
          "low": 4.45,
          "open": 4.47,
          "prev_close": 4.48
        },
        {
          "code": "000089",
          "name": "深圳机场",
          "price": 6.82,
          "pct": 0.59,
          "amount": 0.0,
          "turnover": 0.0,
          "volume_ratio": 0.0,
          "amplitude": 0.0,
          "speed": 0.0,
          "change_5m": 0.0,
          "market_cap_float": 0.0,
          "market_cap_total": 0.0,
          "high": 6.83,
          "low": 6.74,
          "open": 6.76,
          "prev_close": 6.78
        },
        {
          "code": "000090",
          "name": "天健集团",
          "price": 3.28,
          "pct": -1.5015,
          "amount": 0.0,
          "turnover": 0.0,
          "volume_ratio": 0.0,
          "amplitude": 0.0,
          "speed": 0.0,
          "change_5m": 0.0,
          "market_cap_float": 0.0,
          "market_cap_total": 0.0,
          "high": 3.32,
          "low": 3.26,
          "open": 3.31,
          "prev_close": 3.33
        },
        {
          "code": "000096",
          "name": "广聚能源",
          "price": 8.35,
          "pct": -1.1834,
          "amount": 0.0,
          "turnover": 0.0,
          "volume_ratio": 0.0,
          "amplitude": 0.0,
          "speed": 0.0,
          "change_5m": 0.0,
          "market_cap_float": 0.0,
          "market_cap_total": 0.0,
          "high": 8.43,
          "low": 8.24,
          "open": 8.43,
          "prev_close": 8.45
        },
        {
          "code": "000099",
          "name": "中信海直",
          "price": 16.56,
          "pct": -1.5458,
          "amount": 0.0,
          "turnover": 0.0,
          "volume_ratio": 0.0,
          "amplitude": 0.0,
          "speed": 0.0,
          "change_5m": 0.0,
          "market_cap_float": 0.0,
          "market_cap_total": 0.0,
          "high": 16.84,
          "low": 16.35,
          "open": 16.7,
          "prev_close": 16.82
        },
        {
          "code": "000100",
          "name": "TCL科技",
          "price": 4.56,
          "pct": 4.8276,
          "amount": 0.0,
          "turnover": 0.0,
          "volume_ratio": 0.0,
          "amplitude": 0.0,
          "speed": 0.0,
          "change_5m": 0.0,
          "market_cap_float": 0.0,
          "market_cap_total": 0.0,
          "high": 4.64,
          "low": 4.28,
          "open": 4.29,
          "prev_close": 4.35
        },
        {
          "code": "000151",
          "name": "中成股份",
          "price": 11.31,
          "pct": -1.9081,
          "amount": 0.0,
          "turnover": 0.0,
          "volume_ratio": 0.0,
          "amplitude": 0.0,
          "speed": 0.0,
          "change_5m": 0.0,
          "market_cap_float": 0.0,
          "market_cap_total": 0.0,
          "high": 11.51,
          "low": 11.15,
          "open": 11.46,
          "prev_close": 11.53
        }
      ],
      "top_volume_ratio": [
        {
          "code": "000001",
          "name": "平安银行",
          "price": 10.43,
          "pct": 1.07,
          "amount": 900879538.05,
          "turnover": 0.43,
          "volume_ratio": 0.0,
          "amplitude": 1.65,
          "speed": 0.0,
          "change_5m": 0.0,
          "market_cap_float": 0.0,
          "market_cap_total": 0.0,
          "high": 10.47,
          "low": 10.3,
          "open": 10.35,
          "prev_close": 10.32
        },
        {
          "code": "000002",
          "name": "万  科Ａ",
          "price": 3.39,
          "pct": -2.87,
          "amount": 430589235.86,
          "turnover": 1.3,
          "volume_ratio": 0.0,
          "amplitude": 3.44,
          "speed": 0.0,
          "change_5m": 0.0,
          "market_cap_float": 0.0,
          "market_cap_total": 0.0,
          "high": 3.48,
          "low": 3.36,
          "open": 3.46,
          "prev_close": 3.49
        },
        {
          "code": "000006",
          "name": "深振业Ａ",
          "price": 10.26,
          "pct": -1.5355,
          "amount": 0.0,
          "turnover": 0.0,
          "volume_ratio": 0.0,
          "amplitude": 0.0,
          "speed": 0.0,
          "change_5m": 0.0,
          "market_cap_float": 0.0,
          "market_cap_total": 0.0,
          "high": 10.43,
          "low": 9.92,
          "open": 10.34,
          "prev_close": 10.42
        },
        {
          "code": "000007",
          "name": "全新好",
          "price": 12.23,
          "pct": -2.8594,
          "amount": 0.0,
          "turnover": 0.0,
          "volume_ratio": 0.0,
          "amplitude": 0.0,
          "speed": 0.0,
          "change_5m": 0.0,
          "market_cap_float": 0.0,
          "market_cap_total": 0.0,
          "high": 12.59,
          "low": 12.05,
          "open": 12.39,
          "prev_close": 12.59
        },
        {
          "code": "000008",
          "name": "神州高铁",
          "price": 2.57,
          "pct": -1.5326,
          "amount": 0.0,
          "turnover": 0.0,
          "volume_ratio": 0.0,
          "amplitude": 0.0,
          "speed": 0.0,
          "change_5m": 0.0,
          "market_cap_float": 0.0,
          "market_cap_total": 0.0,
          "high": 2.61,
          "low": 2.56,
          "open": 2.6,
          "prev_close": 2.61
        },
        {
          "code": "000009",
          "name": "中国宝安",
          "price": 7.57,
          "pct": 0.3979,
          "amount": 0.0,
          "turnover": 0.0,
          "volume_ratio": 0.0,
          "amplitude": 0.0,
          "speed": 0.0,
          "change_5m": 0.0,
          "market_cap_float": 0.0,
          "market_cap_total": 0.0,
          "high": 7.59,
          "low": 7.46,
          "open": 7.51,
          "prev_close": 7.54
        },
        {
          "code": "000011",
          "name": "深物业A",
          "price": 7.34,
          "pct": -1.7403,
          "amount": 0.0,
          "turnover": 0.0,
          "volume_ratio": 0.0,
          "amplitude": 0.0,
          "speed": 0.0,
          "change_5m": 0.0,
          "market_cap_float": 0.0,
          "market_cap_total": 0.0,
          "high": 7.47,
          "low": 7.28,
          "open": 7.43,
          "prev_close": 7.47
        },
        {
          "code": "000012",
          "name": "南 玻Ａ",
          "price": 4.5,
          "pct": -2.1739,
          "amount": 0.0,
          "turnover": 0.0,
          "volume_ratio": 0.0,
          "amplitude": 0.0,
          "speed": 0.0,
          "change_5m": 0.0,
          "market_cap_float": 0.0,
          "market_cap_total": 0.0,
          "high": 4.73,
          "low": 4.36,
          "open": 4.37,
          "prev_close": 4.6
        },
        {
          "code": "000014",
          "name": "沙河股份",
          "price": 10.9,
          "pct": -2.5045,
          "amount": 0.0,
          "turnover": 0.0,
          "volume_ratio": 0.0,
          "amplitude": 0.0,
          "speed": 0.0,
          "change_5m": 0.0,
          "market_cap_float": 0.0,
          "market_cap_total": 0.0,
          "high": 11.18,
          "low": 10.78,
          "open": 11.1,
          "prev_close": 11.18
        },
        {
          "code": "000017",
          "name": "深中华A",
          "price": 5.56,
          "pct": -1.5929,
          "amount": 0.0,
          "turnover": 0.0,
          "volume_ratio": 0.0,
          "amplitude": 0.0,
          "speed": 0.0,
          "change_5m": 0.0,
          "market_cap_float": 0.0,
          "market_cap_total": 0.0,
          "high": 5.65,
          "low": 5.47,
          "open": 5.62,
          "prev_close": 5.65
        },
        {
          "code": "000019",
          "name": "深粮控股",
          "price": 6.54,
          "pct": -1.059,
          "amount": 0.0,
          "turnover": 0.0,
          "volume_ratio": 0.0,
          "amplitude": 0.0,
          "speed": 0.0,
          "change_5m": 0.0,
          "market_cap_float": 0.0,
          "market_cap_total": 0.0,
          "high": 6.61,
          "low": 6.45,
          "open": 6.6,
          "prev_close": 6.61
        },
        {
          "code": "000020",
          "name": "深华发Ａ",
          "price": 12.97,
          "pct": -0.077,
          "amount": 0.0,
          "turnover": 0.0,
          "volume_ratio": 0.0,
          "amplitude": 0.0,
          "speed": 0.0,
          "change_5m": 0.0,
          "market_cap_float": 0.0,
          "market_cap_total": 0.0,
          "high": 13.03,
          "low": 12.71,
          "open": 12.87,
          "prev_close": 12.98
        },
        {
          "code": "000021",
          "name": "深科技",
          "price": 42.53,
          "pct": 3.9091,
          "amount": 0.0,
          "turnover": 0.0,
          "volume_ratio": 0.0,
          "amplitude": 0.0,
          "speed": 0.0,
          "change_5m": 0.0,
          "market_cap_float": 0.0,
          "market_cap_total": 0.0,
          "high": 44.91,
          "low": 38.49,
          "open": 41.28,
          "prev_close": 40.93
        },
        {
          "code": "000025",
          "name": "特 力Ａ",
          "price": 14.62,
          "pct": -0.6118,
          "amount": 0.0,
          "turnover": 0.0,
          "volume_ratio": 0.0,
          "amplitude": 0.0,
          "speed": 0.0,
          "change_5m": 0.0,
          "market_cap_float": 0.0,
          "market_cap_total": 0.0,
          "high": 14.71,
          "low": 14.36,
          "open": 14.66,
          "prev_close": 14.71
        },
        {
          "code": "000026",
          "name": "飞亚达",
          "price": 24.22,
          "pct": -10.0297,
          "amount": 0.0,
          "turnover": 0.0,
          "volume_ratio": 0.0,
          "amplitude": 0.0,
          "speed": 0.0,
          "change_5m": 0.0,
          "market_cap_float": 0.0,
          "market_cap_total": 0.0,
          "high": 25.47,
          "low": 24.22,
          "open": 25.13,
          "prev_close": 26.92
        },
        {
          "code": "000027",
          "name": "深圳能源",
          "price": 7.62,
          "pct": 0.7937,
          "amount": 0.0,
          "turnover": 0.0,
          "volume_ratio": 0.0,
          "amplitude": 0.0,
          "speed": 0.0,
          "change_5m": 0.0,
          "market_cap_float": 0.0,
          "market_cap_total": 0.0,
          "high": 7.7,
          "low": 7.37,
          "open": 7.49,
          "prev_close": 7.56
        },
        {
          "code": "000028",
          "name": "国药一致",
          "price": 23.58,
          "pct": -0.5063,
          "amount": 0.0,
          "turnover": 0.0,
          "volume_ratio": 0.0,
          "amplitude": 0.0,
          "speed": 0.0,
          "change_5m": 0.0,
          "market_cap_float": 0.0,
          "market_cap_total": 0.0,
          "high": 23.73,
          "low": 23.49,
          "open": 23.73,
          "prev_close": 23.7
        },
        {
          "code": "000029",
          "name": "深深房Ａ",
          "price": 24.915,
          "pct": 0.7277,
          "amount": 0.0,
          "turnover": 0.0,
          "volume_ratio": 0.0,
          "amplitude": 0.0,
          "speed": 0.0,
          "change_5m": 0.0,
          "market_cap_float": 0.0,
          "market_cap_total": 0.0,
          "high": 25.245,
          "low": 24.325,
          "open": 24.775,
          "prev_close": 24.735
        },
        {
          "code": "000030",
          "name": "富奥股份",
          "price": 4.75,
          "pct": -0.2101,
          "amount": 0.0,
          "turnover": 0.0,
          "volume_ratio": 0.0,
          "amplitude": 0.0,
          "speed": 0.0,
          "change_5m": 0.0,
          "market_cap_float": 0.0,
          "market_cap_total": 0.0,
          "high": 4.77,
          "low": 4.69,
          "open": 4.74,
          "prev_close": 4.76
        },
        {
          "code": "000031",
          "name": "大悦城",
          "price": 2.59,
          "pct": -2.6316,
          "amount": 0.0,
          "turnover": 0.0,
          "volume_ratio": 0.0,
          "amplitude": 0.0,
          "speed": 0.0,
          "change_5m": 0.0,
          "market_cap_float": 0.0,
          "market_cap_total": 0.0,
          "high": 2.67,
          "low": 2.56,
          "open": 2.66,
          "prev_close": 2.66
        },
        {
          "code": "000032",
          "name": "深桑达Ａ",
          "price": 18.285,
          "pct": -3.1258,
          "amount": 0.0,
          "turnover": 0.0,
          "volume_ratio": 0.0,
          "amplitude": 0.0,
          "speed": 0.0,
          "change_5m": 0.0,
          "market_cap_float": 0.0,
          "market_cap_total": 0.0,
          "high": 18.765,
          "low": 17.845,
          "open": 18.745,
          "prev_close": 18.875
        },
        {
          "code": "000034",
          "name": "神州数码",
          "price": 27.87,
          "pct": -5.5894,
          "amount": 0.0,
          "turnover": 0.0,
          "volume_ratio": 0.0,
          "amplitude": 0.0,
          "speed": 0.0,
          "change_5m": 0.0,
          "market_cap_float": 0.0,
          "market_cap_total": 0.0,
          "high": 29.2,
          "low": 27.43,
          "open": 29.2,
          "prev_close": 29.52
        },
        {
          "code": "000035",
          "name": "中国天楹",
          "price": 6.08,
          "pct": 2.5295,
          "amount": 0.0,
          "turnover": 0.0,
          "volume_ratio": 0.0,
          "amplitude": 0.0,
          "speed": 0.0,
          "change_5m": 0.0,
          "market_cap_float": 0.0,
          "market_cap_total": 0.0,
          "high": 6.11,
          "low": 5.81,
          "open": 5.93,
          "prev_close": 5.93
        },
        {
          "code": "000036",
          "name": "华联控股",
          "price": 5.39,
          "pct": 0.1859,
          "amount": 0.0,
          "turnover": 0.0,
          "volume_ratio": 0.0,
          "amplitude": 0.0,
          "speed": 0.0,
          "change_5m": 0.0,
          "market_cap_float": 0.0,
          "market_cap_total": 0.0,
          "high": 5.51,
          "low": 5.3,
          "open": 5.36,
          "prev_close": 5.38
        },
        {
          "code": "000037",
          "name": "深南电A",
          "price": 9.88,
          "pct": -1.2,
          "amount": 0.0,
          "turnover": 0.0,
          "volume_ratio": 0.0,
          "amplitude": 0.0,
          "speed": 0.0,
          "change_5m": 0.0,
          "market_cap_float": 0.0,
          "market_cap_total": 0.0,
          "high": 10.06,
          "low": 9.62,
          "open": 10.01,
          "prev_close": 10.0
        },
        {
          "code": "000039",
          "name": "中集集团",
          "price": 10.11,
          "pct": -0.0988,
          "amount": 0.0,
          "turnover": 0.0,
          "volume_ratio": 0.0,
          "amplitude": 0.0,
          "speed": 0.0,
          "change_5m": 0.0,
          "market_cap_float": 0.0,
          "market_cap_total": 0.0,
          "high": 10.18,
          "low": 9.8,
          "open": 10.13,
          "prev_close": 10.12
        },
        {
          "code": "000042",
          "name": "中洲控股",
          "price": 9.94,
          "pct": -1.9724,
          "amount": 0.0,
          "turnover": 0.0,
          "volume_ratio": 0.0,
          "amplitude": 0.0,
          "speed": 0.0,
          "change_5m": 0.0,
          "market_cap_float": 0.0,
          "market_cap_total": 0.0,
          "high": 10.14,
          "low": 9.64,
          "open": 10.14,
          "prev_close": 10.14
        },
        {
          "code": "000045",
          "name": "深纺织Ａ",
          "price": 12.012,
          "pct": -0.0832,
          "amount": 0.0,
          "turnover": 0.0,
          "volume_ratio": 0.0,
          "amplitude": 0.0,
          "speed": 0.0,
          "change_5m": 0.0,
          "market_cap_float": 0.0,
          "market_cap_total": 0.0,
          "high": 12.192,
          "low": 11.842,
          "open": 11.982,
          "prev_close": 12.022
        },
        {
          "code": "000048",
          "name": "京基智农",
          "price": 13.28,
          "pct": -1.0432,
          "amount": 0.0,
          "turnover": 0.0,
          "volume_ratio": 0.0,
          "amplitude": 0.0,
          "speed": 0.0,
          "change_5m": 0.0,
          "market_cap_float": 0.0,
          "market_cap_total": 0.0,
          "high": 13.45,
          "low": 13.1,
          "open": 13.44,
          "prev_close": 13.42
        },
        {
          "code": "000049",
          "name": "德赛电池",
          "price": 26.33,
          "pct": -1.2378,
          "amount": 0.0,
          "turnover": 0.0,
          "volume_ratio": 0.0,
          "amplitude": 0.0,
          "speed": 0.0,
          "change_5m": 0.0,
          "market_cap_float": 0.0,
          "market_cap_total": 0.0,
          "high": 26.74,
          "low": 25.97,
          "open": 26.6,
          "prev_close": 26.66
        },
        {
          "code": "000050",
          "name": "深天马Ａ",
          "price": 8.27,
          "pct": 2.6055,
          "amount": 0.0,
          "turnover": 0.0,
          "volume_ratio": 0.0,
          "amplitude": 0.0,
          "speed": 0.0,
          "change_5m": 0.0,
          "market_cap_float": 0.0,
          "market_cap_total": 0.0,
          "high": 8.4,
          "low": 7.94,
          "open": 7.98,
          "prev_close": 8.06
        },
        {
          "code": "000055",
          "name": "方大集团",
          "price": 3.48,
          "pct": -2.521,
          "amount": 0.0,
          "turnover": 0.0,
          "volume_ratio": 0.0,
          "amplitude": 0.0,
          "speed": 0.0,
          "change_5m": 0.0,
          "market_cap_float": 0.0,
          "market_cap_total": 0.0,
          "high": 3.58,
          "low": 3.44,
          "open": 3.57,
          "prev_close": 3.57
        },
        {
          "code": "000058",
          "name": "深 赛 格",
          "price": 7.326,
          "pct": -2.6575,
          "amount": 0.0,
          "turnover": 0.0,
          "volume_ratio": 0.0,
          "amplitude": 0.0,
          "speed": 0.0,
          "change_5m": 0.0,
          "market_cap_float": 0.0,
          "market_cap_total": 0.0,
          "high": 7.536,
          "low": 7.216,
          "open": 7.506,
          "prev_close": 7.526
        },
        {
          "code": "000059",
          "name": "华锦股份",
          "price": 4.57,
          "pct": -0.2183,
          "amount": 0.0,
          "turnover": 0.0,
          "volume_ratio": 0.0,
          "amplitude": 0.0,
          "speed": 0.0,
          "change_5m": 0.0,
          "market_cap_float": 0.0,
          "market_cap_total": 0.0,
          "high": 4.59,
          "low": 4.51,
          "open": 4.57,
          "prev_close": 4.58
        },
        {
          "code": "000060",
          "name": "中金岭南",
          "price": 7.9,
          "pct": 2.5974,
          "amount": 0.0,
          "turnover": 0.0,
          "volume_ratio": 0.0,
          "amplitude": 0.0,
          "speed": 0.0,
          "change_5m": 0.0,
          "market_cap_float": 0.0,
          "market_cap_total": 0.0,
          "high": 8.02,
          "low": 7.43,
          "open": 7.69,
          "prev_close": 7.7
        },
        {
          "code": "000061",
          "name": "农 产 品",
          "price": 6.55,
          "pct": -0.1524,
          "amount": 0.0,
          "turnover": 0.0,
          "volume_ratio": 0.0,
          "amplitude": 0.0,
          "speed": 0.0,
          "change_5m": 0.0,
          "market_cap_float": 0.0,
          "market_cap_total": 0.0,
          "high": 6.65,
          "low": 6.48,
          "open": 6.53,
          "prev_close": 6.56
        },
        {
          "code": "000062",
          "name": "深圳华强",
          "price": 33.66,
          "pct": -6.9652,
          "amount": 0.0,
          "turnover": 0.0,
          "volume_ratio": 0.0,
          "amplitude": 0.0,
          "speed": 0.0,
          "change_5m": 0.0,
          "market_cap_float": 0.0,
          "market_cap_total": 0.0,
          "high": 35.09,
          "low": 33.29,
          "open": 34.82,
          "prev_close": 36.18
        },
        {
          "code": "000063",
          "name": "中兴通讯",
          "price": 35.54,
          "pct": -2.0127,
          "amount": 0.0,
          "turnover": 0.0,
          "volume_ratio": 0.0,
          "amplitude": 0.0,
          "speed": 0.0,
          "change_5m": 0.0,
          "market_cap_float": 0.0,
          "market_cap_total": 0.0,
          "high": 36.0,
          "low": 34.77,
          "open": 36.0,
          "prev_close": 36.27
        },
        {
          "code": "000065",
          "name": "北方国际",
          "price": 12.383,
          "pct": -4.1786,
          "amount": 0.0,
          "turnover": 0.0,
          "volume_ratio": 0.0,
          "amplitude": 0.0,
          "speed": 0.0,
          "change_5m": 0.0,
          "market_cap_float": 0.0,
          "market_cap_total": 0.0,
          "high": 12.583,
          "low": 12.213,
          "open": 12.503,
          "prev_close": 12.923
        },
        {
          "code": "000066",
          "name": "中国长城",
          "price": 19.3,
          "pct": -6.2196,
          "amount": 0.0,
          "turnover": 0.0,
          "volume_ratio": 0.0,
          "amplitude": 0.0,
          "speed": 0.0,
          "change_5m": 0.0,
          "market_cap_float": 0.0,
          "market_cap_total": 0.0,
          "high": 20.0,
          "low": 18.9,
          "open": 20.0,
          "prev_close": 20.58
        },
        {
          "code": "000068",
          "name": "华控赛格",
          "price": 3.01,
          "pct": -2.9032,
          "amount": 0.0,
          "turnover": 0.0,
          "volume_ratio": 0.0,
          "amplitude": 0.0,
          "speed": 0.0,
          "change_5m": 0.0,
          "market_cap_float": 0.0,
          "market_cap_total": 0.0,
          "high": 3.09,
          "low": 2.95,
          "open": 3.09,
          "prev_close": 3.1
        },
        {
          "code": "000069",
          "name": "华侨城Ａ",
          "price": 1.96,
          "pct": -0.5076,
          "amount": 0.0,
          "turnover": 0.0,
          "volume_ratio": 0.0,
          "amplitude": 0.0,
          "speed": 0.0,
          "change_5m": 0.0,
          "market_cap_float": 0.0,
          "market_cap_total": 0.0,
          "high": 1.98,
          "low": 1.93,
          "open": 1.96,
          "prev_close": 1.97
        },
        {
          "code": "000070",
          "name": "特发信息",
          "price": 17.43,
          "pct": -4.8581,
          "amount": 0.0,
          "turnover": 0.0,
          "volume_ratio": 0.0,
          "amplitude": 0.0,
          "speed": 0.0,
          "change_5m": 0.0,
          "market_cap_float": 0.0,
          "market_cap_total": 0.0,
          "high": 18.18,
          "low": 16.88,
          "open": 18.14,
          "prev_close": 18.32
        },
        {
          "code": "000088",
          "name": "盐 田 港",
          "price": 4.5,
          "pct": 0.4464,
          "amount": 0.0,
          "turnover": 0.0,
          "volume_ratio": 0.0,
          "amplitude": 0.0,
          "speed": 0.0,
          "change_5m": 0.0,
          "market_cap_float": 0.0,
          "market_cap_total": 0.0,
          "high": 4.5,
          "low": 4.45,
          "open": 4.47,
          "prev_close": 4.48
        },
        {
          "code": "000089",
          "name": "深圳机场",
          "price": 6.82,
          "pct": 0.59,
          "amount": 0.0,
          "turnover": 0.0,
          "volume_ratio": 0.0,
          "amplitude": 0.0,
          "speed": 0.0,
          "change_5m": 0.0,
          "market_cap_float": 0.0,
          "market_cap_total": 0.0,
          "high": 6.83,
          "low": 6.74,
          "open": 6.76,
          "prev_close": 6.78
        },
        {
          "code": "000090",
          "name": "天健集团",
          "price": 3.28,
          "pct": -1.5015,
          "amount": 0.0,
          "turnover": 0.0,
          "volume_ratio": 0.0,
          "amplitude": 0.0,
          "speed": 0.0,
          "change_5m": 0.0,
          "market_cap_float": 0.0,
          "market_cap_total": 0.0,
          "high": 3.32,
          "low": 3.26,
          "open": 3.31,
          "prev_close": 3.33
        },
        {
          "code": "000096",
          "name": "广聚能源",
          "price": 8.35,
          "pct": -1.1834,
          "amount": 0.0,
          "turnover": 0.0,
          "volume_ratio": 0.0,
          "amplitude": 0.0,
          "speed": 0.0,
          "change_5m": 0.0,
          "market_cap_float": 0.0,
          "market_cap_total": 0.0,
          "high": 8.43,
          "low": 8.24,
          "open": 8.43,
          "prev_close": 8.45
        },
        {
          "code": "000099",
          "name": "中信海直",
          "price": 16.56,
          "pct": -1.5458,
          "amount": 0.0,
          "turnover": 0.0,
          "volume_ratio": 0.0,
          "amplitude": 0.0,
          "speed": 0.0,
          "change_5m": 0.0,
          "market_cap_float": 0.0,
          "market_cap_total": 0.0,
          "high": 16.84,
          "low": 16.35,
          "open": 16.7,
          "prev_close": 16.82
        },
        {
          "code": "000100",
          "name": "TCL科技",
          "price": 4.56,
          "pct": 4.8276,
          "amount": 0.0,
          "turnover": 0.0,
          "volume_ratio": 0.0,
          "amplitude": 0.0,
          "speed": 0.0,
          "change_5m": 0.0,
          "market_cap_float": 0.0,
          "market_cap_total": 0.0,
          "high": 4.64,
          "low": 4.28,
          "open": 4.29,
          "prev_close": 4.35
        },
        {
          "code": "000151",
          "name": "中成股份",
          "price": 11.31,
          "pct": -1.9081,
          "amount": 0.0,
          "turnover": 0.0,
          "volume_ratio": 0.0,
          "amplitude": 0.0,
          "speed": 0.0,
          "change_5m": 0.0,
          "market_cap_float": 0.0,
          "market_cap_total": 0.0,
          "high": 11.51,
          "low": 11.15,
          "open": 11.46,
          "prev_close": 11.53
        }
      ],
      "top_industries": [],
      "top_concepts": [],
      "pool_industry_counts": [],
      "top_industry_fund_flow": [],
      "top_concept_fund_flow": [],
      "top_stock_fund_flow": []
    },
    "pools": {
      "limit_up": [],
      "previous_limit_up": [],
      "strong": [],
      "broken_limit": [],
      "dtgc": []
    }
  },
  "source_status": {
    "stock_spot": {
      "ok": true,
      "rows": 5189,
      "duration_sec": 0.0,
      "error": null,
      "columns": [
        "交易日期",
        "今开",
        "代码",
        "历史数据源",
        "名称",
        "开盘",
        "成交量",
        "成交额",
        "振幅",
        "换手率",
        "收盘",
        "昨收",
        "最低",
        "最新价",
        "最高",
        "涨跌幅",
        "涨跌额"
      ]
    },
    "limit_up_pool": {
      "ok": true,
      "rows": 0,
      "duration_sec": 1.832,
      "error": null,
      "columns": []
    },
    "previous_limit_up_pool": {
      "ok": true,
      "rows": 0,
      "duration_sec": 2.012,
      "error": null,
      "columns": []
    },
    "strong_pool": {
      "ok": true,
      "rows": 0,
      "duration_sec": 2.022,
      "error": null,
      "columns": []
    },
    "broken_limit_pool": {
      "ok": true,
      "rows": 0,
      "duration_sec": 1.993,
      "error": null,
      "columns": []
    },
    "dtgc_pool": {
      "ok": true,
      "rows": 0,
      "duration_sec": 2.003,
      "error": null,
      "columns": []
    }
  }
}