{
  "snapshot_id": "20260526_historical_58457bdd710d2303",
  "mode": "historical",
  "captured_at": "2026-06-21T10:45:03+08:00",
  "source_time": "2026-05-26T15:00:00+08:00",
  "market_date": "20260526",
  "window_valid": true,
  "stock_count": 5189,
  "tradeable_stock_count": 3029,
  "expected_count": 5189,
  "actual_count": 5189,
  "is_complete": true,
  "size_bytes": 2761770,
  "checksum": "471368aff08fc63c05e5d22191dbab2026d6ef3a71218d0aada75a76e0b672fa",
  "download_url": "/v1/market/snapshots/20260526_historical_58457bdd710d2303/export?dataset=stocks"
}